{
  "src/lib/components/DashTabulator.react.js": {
    "description": "",
    "displayName": "DashTabulator",
    "methods": [],
    "props": {
      "id": {
        "type": {
          "name": "string"
        },
        "required": false,
        "description": "The ID used to identify this component in Dash callbacks."
      },
      "columns": {
        "type": {
          "name": "array"
        },
        "required": false,
        "description": "A label that will be printed when this component is rendered.",
        "defaultValue": {
          "value": "[]",
          "computed": false
        }
      },
      "data": {
        "type": {
          "name": "array"
        },
        "required": false,
        "description": "The value displayed in the input.",
        "defaultValue": {
          "value": "[]",
          "computed": false
        }
      },
      "setProps": {
        "type": {
          "name": "func"
        },
        "required": false,
        "description": "Dash-assigned callback that should be called to report property changes\nto Dash, to make them available for callbacks."
      },
      "cellEdited": {
        "type": {
          "name": "object"
        },
        "required": false,
        "description": "cellEdited captures the cell that was clicked on"
      }
    }
  }
}