{
    "meta": {
        "label": "Pivot editlog",
        "description": "Creates a dataset with as many rows as unique keys in the edit log, one column per value of `column_name`, and populates the column with the last edited value.",
        "icon": "icon-puzzle-piece"
    },
    "kind": "PYTHON",
    "inputRoles": [
        {
            "name": "editlog",
            "label": "Edit log",
            "description": "Managed by webapp",
            "arity": "UNARY",
            "required": true,
            "acceptsDataset": true
        }
    ],
    "outputRoles": [
        {
            "name": "editlog_pivoted",
            "label": "Pivoted edit log",
            "description": "",
            "arity": "UNARY",
            "required": true,
            "acceptsDataset": true
        }
    ],
    "params": [
        {
            "name": "webapp_ID",
            "label": "Webapp ID",
            "description": "Do not edit!",
            "type": "TEXT"
        }
    ],
    "resourceKeys": []
}
